auto_navi_system-0.1.0.dist-info/licenses/LICENSE
auto_navigation_system/__init__.py
auto_navigation_system/autoNaviSystem.py
auto_navi_system-0.1.0.dist-info/METADATA
auto_navi_system-0.1.0.dist-info/WHEEL
auto_navi_system-0.1.0.dist-info/top_level.txt
auto_navi_system-0.1.0.dist-info/RECORD
