Metadata-Version: 2.4
Name: auto-navi-system
Version: 0.1.0
Summary: 自主航行测试系统
Author-email: lailonghua <lailonghua666@whut.edu.cn>
License: MIT
Project-URL: Homepage, https://github.com/lailonghua/auto-navi-system
Classifier: Programming Language :: Python :: 3
Classifier: License :: OSI Approved :: MIT License
Classifier: Operating System :: OS Independent
Requires-Python: >=3.6
License-File: LICENSE
Dynamic: license-file
